{
    "project": "openbmc/entity-manager",
    "branch": "master",
    "id": "I79c2b169e6e01754509dc84cb4b8a15c59e122df",
    "number": 46921,
    "subject": "dynamic mux: Add support slot dbus interface",
    "owner": {
        "name": "Vijay Khemka",
        "email": "vijaykhemkalinux@gmail.com",
        "username": "vijaykhemka"
    },
    "url": "https://gerrit.openbmc-project.xyz/c/openbmc/entity-manager/+/46921",
    "commitMessage": "dynamic mux: Add support slot dbus interface\n\nAdded dbus interface for all enumerated slots and also added their types\ninto dbus property.\n\nTested: Verified on target system\n/xyz/openbmc_project/inventory\n      \u251c\u2500/xyz/openbmc_project/inventory/Slot1\n      \u251c\u2500/xyz/openbmc_project/inventory/Slot2\n      \u251c\u2500/xyz/openbmc_project/inventory/Slot3\n      \u251c\u2500/xyz/openbmc_project/inventory/Slot4\n\nSigned-off-by: Vijay Khemka <vijaykhemkalinux@gmail.com>\nChange-Id: I79c2b169e6e01754509dc84cb4b8a15c59e122df\n",
    "createdOn": 1631744971,
    "lastUpdated": 1636757776,
    "open": true,
    "status": "NEW",
    "comments": [
        {
            "timestamp": 1631744971,
            "reviewer": {
                "name": "Vijay Khemka",
                "email": "vijaykhemkalinux@gmail.com",
                "username": "vijaykhemka"
            },
            "message": "Uploaded patch set 1."
        },
        {
            "timestamp": 1631744983,
            "reviewer": {
                "name": "OpenBMC CI",
                "email": "openbmcbump-ci@yahoo.com",
                "username": "jenkins-openbmc-ci"
            },
            "message": "Patch Set 1: Ok-To-Test+1\n\nUser approved, CI ok to start"
        },
        {
            "timestamp": 1631745326,
            "reviewer": {
                "name": "OpenBMC CI",
                "email": "openbmcbump-ci@yahoo.com",
                "username": "jenkins-openbmc-ci"
            },
            "message": "Patch Set 1: Verified-1\n\nBuild Failed \n\nhttps://jenkins.openbmc.org/job/ci-repository/26408/ : FAILURE"
        },
        {
            "timestamp": 1631745813,
            "reviewer": {
                "name": "Vijay Khemka",
                "email": "vijaykhemkalinux@gmail.com",
                "username": "vijaykhemka"
            },
            "message": "Uploaded patch set 2: Patch Set 1 was rebased."
        },
        {
            "timestamp": 1631745844,
            "reviewer": {
                "name": "OpenBMC CI",
                "email": "openbmcbump-ci@yahoo.com",
                "username": "jenkins-openbmc-ci"
            },
            "message": "Patch Set 2: Ok-To-Test+1\n\nUser approved, CI ok to start"
        },
        {
            "timestamp": 1631746111,
            "reviewer": {
                "name": "OpenBMC CI",
                "email": "openbmcbump-ci@yahoo.com",
                "username": "jenkins-openbmc-ci"
            },
            "message": "Patch Set 2: Verified+1\n\nBuild Successful \n\nhttps://jenkins.openbmc.org/job/ci-repository/26411/ : SUCCESS"
        },
        {
            "timestamp": 1632190553,
            "reviewer": {
                "name": "Vijay Khemka",
                "email": "vijaykhemkalinux@gmail.com",
                "username": "vijaykhemka"
            },
            "message": "Uploaded patch set 3: Patch Set 2 was rebased."
        },
        {
            "timestamp": 1632190576,
            "reviewer": {
                "name": "OpenBMC CI",
                "email": "openbmcbump-ci@yahoo.com",
                "username": "jenkins-openbmc-ci"
            },
            "message": "Patch Set 3: Ok-To-Test+1\n\nUser approved, CI ok to start"
        },
        {
            "timestamp": 1632190829,
            "reviewer": {
                "name": "OpenBMC CI",
                "email": "openbmcbump-ci@yahoo.com",
                "username": "jenkins-openbmc-ci"
            },
            "message": "Patch Set 3: Verified+1\n\nBuild Successful \n\nhttps://jenkins.openbmc.org/job/ci-repository/26640/ : SUCCESS"
        },
        {
            "timestamp": 1632211640,
            "reviewer": {
                "name": "Andrei Kartashev",
                "email": "a.kartashev@yadro.com",
                "username": "alatarum"
            },
            "message": "Patch Set 3:\n\n(1 comment)"
        },
        {
            "timestamp": 1632222817,
            "reviewer": {
                "name": "Arun Lal K M",
                "email": "arun.lal@intel.com",
                "username": "arunlalkm-intel"
            },
            "message": "Patch Set 3:\n\n(2 comments)"
        },
        {
            "timestamp": 1632433546,
            "reviewer": {
                "name": "Vijay Khemka",
                "email": "vijaykhemkalinux@gmail.com",
                "username": "vijaykhemka"
            },
            "message": "Patch Set 3:\n\n(2 comments)"
        },
        {
            "timestamp": 1632435080,
            "reviewer": {
                "name": "Vijay Khemka",
                "email": "vijaykhemkalinux@gmail.com",
                "username": "vijaykhemka"
            },
            "message": "Uploaded patch set 4."
        },
        {
            "timestamp": 1632435093,
            "reviewer": {
                "name": "OpenBMC CI",
                "email": "openbmcbump-ci@yahoo.com",
                "username": "jenkins-openbmc-ci"
            },
            "message": "Patch Set 4: Ok-To-Test+1\n\nUser approved, CI ok to start"
        },
        {
            "timestamp": 1632435388,
            "reviewer": {
                "name": "OpenBMC CI",
                "email": "openbmcbump-ci@yahoo.com",
                "username": "jenkins-openbmc-ci"
            },
            "message": "Patch Set 4: Verified+1\n\nBuild Successful \n\nhttps://jenkins.openbmc.org/job/ci-repository/26886/ : SUCCESS"
        },
        {
            "timestamp": 1632475095,
            "reviewer": {
                "name": "Andrei Kartashev",
                "email": "a.kartashev@yadro.com",
                "username": "alatarum"
            },
            "message": "Patch Set 4:\n\n(2 comments)"
        },
        {
            "timestamp": 1632475150,
            "reviewer": {
                "name": "Andrei Kartashev",
                "email": "a.kartashev@yadro.com",
                "username": "alatarum"
            },
            "message": "Patch Set 4: Code-Review+1\n\n(1 comment)"
        },
        {
            "timestamp": 1633131448,
            "reviewer": {
                "name": "Zhikui Ren",
                "email": "zhikui.ren@intel.com",
                "username": "ZhikuiRen"
            },
            "message": "Patch Set 4:\n\n(1 comment)"
        },
        {
            "timestamp": 1633477407,
            "reviewer": {
                "name": "Vijay Khemka",
                "email": "vijaykhemkalinux@gmail.com",
                "username": "vijaykhemka"
            },
            "message": "Patch Set 4:\n\n(1 comment)"
        },
        {
            "timestamp": 1633481695,
            "reviewer": {
                "name": "Jie Yang",
                "email": "jjy@google.com",
                "username": "PlotCondor"
            },
            "message": "Patch Set 4:\n\n(2 comments)"
        },
        {
            "timestamp": 1633569543,
            "reviewer": {
                "name": "Vijay Khemka",
                "email": "vijaykhemkalinux@gmail.com",
                "username": "vijaykhemka"
            },
            "message": "Uploaded patch set 5: Commit message was updated."
        },
        {
            "timestamp": 1633636896,
            "reviewer": {
                "name": "Vijay Khemka",
                "email": "vijaykhemkalinux@gmail.com",
                "username": "vijaykhemka"
            },
            "message": "Patch Set 5:\n\n(2 comments)"
        },
        {
            "timestamp": 1634771347,
            "reviewer": {
                "name": "Vijay Khemka",
                "email": "vijaykhemkalinux@gmail.com",
                "username": "vijaykhemka"
            },
            "message": "Uploaded patch set 6."
        },
        {
            "timestamp": 1634771360,
            "reviewer": {
                "name": "OpenBMC CI",
                "email": "openbmcbump-ci@yahoo.com",
                "username": "jenkins-openbmc-ci"
            },
            "message": "Patch Set 6: Ok-To-Test+1\n\nUser approved, CI ok to start"
        },
        {
            "timestamp": 1634771612,
            "reviewer": {
                "name": "OpenBMC CI",
                "email": "openbmcbump-ci@yahoo.com",
                "username": "jenkins-openbmc-ci"
            },
            "message": "Patch Set 6: Verified+1\n\nBuild Successful \n\nhttps://jenkins.openbmc.org/job/ci-repository/28678/ : SUCCESS"
        },
        {
            "timestamp": 1635774912,
            "reviewer": {
                "name": "Andrei Kartashev",
                "email": "a.kartashev@yadro.com",
                "username": "alatarum"
            },
            "message": "Patch Set 6:\n\n(1 comment)"
        },
        {
            "timestamp": 1635880136,
            "reviewer": {
                "name": "Vijay Khemka",
                "email": "vijaykhemkalinux@gmail.com",
                "username": "vijaykhemka"
            },
            "message": "Patch Set 6:\n\n(1 comment)"
        },
        {
            "timestamp": 1635883043,
            "reviewer": {
                "name": "Vijay Khemka",
                "email": "vijaykhemkalinux@gmail.com",
                "username": "vijaykhemka"
            },
            "message": "Uploaded patch set 7."
        },
        {
            "timestamp": 1635883061,
            "reviewer": {
                "name": "OpenBMC CI",
                "email": "openbmcbump-ci@yahoo.com",
                "username": "jenkins-openbmc-ci"
            },
            "message": "Patch Set 7: Ok-To-Test+1\n\nUser approved, CI ok to start"
        },
        {
            "timestamp": 1635883996,
            "reviewer": {
                "name": "OpenBMC CI",
                "email": "openbmcbump-ci@yahoo.com",
                "username": "jenkins-openbmc-ci"
            },
            "message": "Patch Set 7: Verified+1\n\nBuild Successful \n\nhttps://jenkins.openbmc.org/job/ci-repository/29569/ : SUCCESS"
        },
        {
            "timestamp": 1635886072,
            "reviewer": {
                "name": "Zhikui Ren",
                "email": "zhikui.ren@intel.com",
                "username": "ZhikuiRen"
            },
            "message": "Patch Set 7:\n\n(1 comment)"
        },
        {
            "timestamp": 1635890396,
            "reviewer": {
                "name": "Vijay Khemka",
                "email": "vijaykhemkalinux@gmail.com",
                "username": "vijaykhemka"
            },
            "message": "Patch Set 7:\n\n(1 comment)"
        },
        {
            "timestamp": 1636052618,
            "reviewer": {
                "name": "Vijay Khemka",
                "email": "vijaykhemkalinux@gmail.com",
                "username": "vijaykhemka"
            },
            "message": "Uploaded patch set 8."
        },
        {
            "timestamp": 1636052632,
            "reviewer": {
                "name": "OpenBMC CI",
                "email": "openbmcbump-ci@yahoo.com",
                "username": "jenkins-openbmc-ci"
            },
            "message": "Patch Set 8: Ok-To-Test+1\n\nUser approved, CI ok to start"
        },
        {
            "timestamp": 1636052934,
            "reviewer": {
                "name": "OpenBMC CI",
                "email": "openbmcbump-ci@yahoo.com",
                "username": "jenkins-openbmc-ci"
            },
            "message": "Patch Set 8: Verified+1\n\nBuild Successful \n\nhttps://jenkins.openbmc.org/job/ci-repository/29814/ : SUCCESS"
        },
        {
            "timestamp": 1636755216,
            "reviewer": {
                "name": "Vijay Khemka",
                "email": "vijaykhemkalinux@gmail.com",
                "username": "vijaykhemka"
            },
            "message": "Patch Set 8:\n\nping... Please provide your valuable feedback. I have tried to cover all respective comments."
        },
        {
            "timestamp": 1636757776,
            "reviewer": {
                "name": "Vijay Khemka",
                "email": "vijaykhemkalinux@gmail.com",
                "username": "vijaykhemka"
            },
            "message": "Uploaded patch set 9: Commit message was updated."
        }
    ],
    "patchSets": [
        {
            "number": 1,
            "revision": "566924344daebbffbd9b1b69ea343771b94ba546",
            "parents": [
                "29d231249ed5b04889ec91892c86083fb78bc8e5"
            ],
            "ref": "refs/changes/21/46921/1",
            "uploader": {
                "name": "Vijay Khemka",
                "email": "vijaykhemkalinux@gmail.com",
                "username": "vijaykhemka"
            },
            "createdOn": 1631744971,
            "author": {
                "name": "Vijay Khemka",
                "email": "vijaykhemkalinux@gmail.com",
                "username": "vijaykhemka"
            },
            "kind": "REWORK",
            "files": [
                {
                    "file": "/COMMIT_MSG",
                    "type": "ADDED",
                    "insertions": 20,
                    "deletions": 0
                },
                {
                    "file": "include/Overlay.hpp",
                    "type": "MODIFIED",
                    "insertions": 2,
                    "deletions": -1
                },
                {
                    "file": "src/EntityManager.cpp",
                    "type": "MODIFIED",
                    "insertions": 1,
                    "deletions": -1
                },
                {
                    "file": "src/Overlay.cpp",
                    "type": "MODIFIED",
                    "insertions": 32,
                    "deletions": -5
                }
            ],
            "sizeInsertions": 35,
            "sizeDeletions": 7
        },
        {
            "number": 2,
            "revision": "cf4d3f7e972c4478aa5df3299a18e0643e3d5bc7",
            "parents": [
                "cabf8360e58a5d4a4a17689d31a2bd8ed6e2e452"
            ],
            "ref": "refs/changes/21/46921/2",
            "uploader": {
                "name": "Vijay Khemka",
                "email": "vijaykhemkalinux@gmail.com",
                "username": "vijaykhemka"
            },
            "createdOn": 1631745813,
            "author": {
                "name": "Vijay Khemka",
                "email": "vijaykhemkalinux@gmail.com",
                "username": "vijaykhemka"
            },
            "kind": "TRIVIAL_REBASE",
            "files": [
                {
                    "file": "/COMMIT_MSG",
                    "type": "ADDED",
                    "insertions": 20,
                    "deletions": 0
                },
                {
                    "file": "include/Overlay.hpp",
                    "type": "MODIFIED",
                    "insertions": 2,
                    "deletions": -1
                },
                {
                    "file": "src/EntityManager.cpp",
                    "type": "MODIFIED",
                    "insertions": 1,
                    "deletions": -1
                },
                {
                    "file": "src/Overlay.cpp",
                    "type": "MODIFIED",
                    "insertions": 32,
                    "deletions": -5
                }
            ],
            "sizeInsertions": 35,
            "sizeDeletions": 7
        },
        {
            "number": 3,
            "revision": "d0ff946f86f0e5b6fce4b7c381c41919909e933d",
            "parents": [
                "a5dcce6337b0a5283cc5c327f1f0b8bbb2e4e3aa"
            ],
            "ref": "refs/changes/21/46921/3",
            "uploader": {
                "name": "Vijay Khemka",
                "email": "vijaykhemkalinux@gmail.com",
                "username": "vijaykhemka"
            },
            "createdOn": 1632190553,
            "author": {
                "name": "Vijay Khemka",
                "email": "vijaykhemkalinux@gmail.com",
                "username": "vijaykhemka"
            },
            "kind": "TRIVIAL_REBASE",
            "comments": [
                {
                    "file": "src/Overlay.cpp",
                    "line": 156,
                    "reviewer": {
                        "name": "Andrei Kartashev",
                        "email": "a.kartashev@yadro.com",
                        "username": "alatarum"
                    },
                    "message": "Why only this two supported? The interface define much more variants.\n\nBTW: I guess, it supposed to be `&&`"
                },
                {
                    "file": "src/Overlay.cpp",
                    "line": 156,
                    "reviewer": {
                        "name": "Arun Lal K M",
                        "email": "arun.lal@intel.com",
                        "username": "arunlalkm-intel"
                    },
                    "message": "I support Andrei Kartashev, it should be &&"
                },
                {
                    "file": "src/Overlay.cpp",
                    "line": 156,
                    "reviewer": {
                        "name": "Vijay Khemka",
                        "email": "vijaykhemkalinux@gmail.com",
                        "username": "vijaykhemka"
                    },
                    "message": "yes, it should be &&. Mainly these 2 are being used mostly. Can definitely add more later"
                },
                {
                    "file": "src/Overlay.cpp",
                    "line": 156,
                    "reviewer": {
                        "name": "Vijay Khemka",
                        "email": "vijaykhemkalinux@gmail.com",
                        "username": "vijaykhemka"
                    },
                    "message": "Ack"
                },
                {
                    "file": "src/Overlay.cpp",
                    "line": 156,
                    "reviewer": {
                        "name": "Andrei Kartashev",
                        "email": "a.kartashev@yadro.com",
                        "username": "alatarum"
                    },
                    "message": "On our system we also have normal PCIe slots (FullLength) and OCP3 slots (don't actually know small or large). I would definitely want to describe them too. Lets add all variants, provided by the interface from beginning."
                },
                {
                    "file": "src/Overlay.cpp",
                    "line": 156,
                    "reviewer": {
                        "name": "Andrei Kartashev",
                        "email": "a.kartashev@yadro.com",
                        "username": "alatarum"
                    },
                    "message": "Ack"
                },
                {
                    "file": "src/Overlay.cpp",
                    "line": 163,
                    "reviewer": {
                        "name": "Arun Lal K M",
                        "email": "arun.lal@intel.com",
                        "username": "arunlalkm-intel"
                    },
                    "message": "Are we initializing even if slotTypeName is \"Unknown\"?"
                },
                {
                    "file": "src/Overlay.cpp",
                    "line": 163,
                    "reviewer": {
                        "name": "Andrei Kartashev",
                        "email": "a.kartashev@yadro.com",
                        "username": "alatarum"
                    },
                    "message": "We definitely should initialize the interface if type is unknown: it is still slot, even we don't  know about its type."
                }
            ],
            "files": [
                {
                    "file": "/COMMIT_MSG",
                    "type": "ADDED",
                    "insertions": 20,
                    "deletions": 0
                },
                {
                    "file": "include/Overlay.hpp",
                    "type": "MODIFIED",
                    "insertions": 2,
                    "deletions": -1
                },
                {
                    "file": "src/EntityManager.cpp",
                    "type": "MODIFIED",
                    "insertions": 1,
                    "deletions": -1
                },
                {
                    "file": "src/Overlay.cpp",
                    "type": "MODIFIED",
                    "insertions": 32,
                    "deletions": -5
                }
            ],
            "sizeInsertions": 35,
            "sizeDeletions": 7
        },
        {
            "number": 4,
            "revision": "cf16b833ed96b8f74f5172d7c08802281b3df78b",
            "parents": [
                "a5dcce6337b0a5283cc5c327f1f0b8bbb2e4e3aa"
            ],
            "ref": "refs/changes/21/46921/4",
            "uploader": {
                "name": "Vijay Khemka",
                "email": "vijaykhemkalinux@gmail.com",
                "username": "vijaykhemka"
            },
            "createdOn": 1632435080,
            "author": {
                "name": "Vijay Khemka",
                "email": "vijaykhemkalinux@gmail.com",
                "username": "vijaykhemka"
            },
            "kind": "REWORK",
            "comments": [
                {
                    "file": "/COMMIT_MSG",
                    "line": 14,
                    "reviewer": {
                        "name": "Jie Yang",
                        "email": "jjy@google.com",
                        "username": "PlotCondor"
                    },
                    "message": "add your entity config as an example and dbus interface/porperty"
                },
                {
                    "file": "/COMMIT_MSG",
                    "line": 14,
                    "reviewer": {
                        "name": "Vijay Khemka",
                        "email": "vijaykhemkalinux@gmail.com",
                        "username": "vijaykhemka"
                    },
                    "message": "Ack"
                },
                {
                    "file": "src/Overlay.cpp",
                    "line": 159,
                    "reviewer": {
                        "name": "Zhikui Ren",
                        "email": "zhikui.ren@intel.com",
                        "username": "ZhikuiRen"
                    },
                    "message": "Is PCIeSlot the only slot type? There are muxes that are not tied to PCIeSlot"
                },
                {
                    "file": "src/Overlay.cpp",
                    "line": 159,
                    "reviewer": {
                        "name": "Vijay Khemka",
                        "email": "vijaykhemkalinux@gmail.com",
                        "username": "vijaykhemka"
                    },
                    "message": "This is the only type defined by PDI. We can certainly add more in future."
                },
                {
                    "file": "src/Overlay.cpp",
                    "line": 159,
                    "reviewer": {
                        "name": "Jie Yang",
                        "email": "jjy@google.com",
                        "username": "PlotCondor"
                    },
                    "message": "To be consistent with entity manager code, the object path of slots exposed by an entity config should have the prefix of entity dbus object path.\n\nI also suggest to create the dbus objects in EntityManager.cpp."
                },
                {
                    "file": "src/Overlay.cpp",
                    "line": 159,
                    "reviewer": {
                        "name": "Vijay Khemka",
                        "email": "vijaykhemkalinux@gmail.com",
                        "username": "vijaykhemka"
                    },
                    "message": "all slots are enumerated here so it would be better to create dbus objects here only. And I didn't understand about prefix in object path. This will be associated with actual cards if any detected."
                },
                {
                    "file": "src/Overlay.cpp",
                    "line": 159,
                    "reviewer": {
                        "name": "Zhikui Ren",
                        "email": "zhikui.ren@intel.com",
                        "username": "ZhikuiRen"
                    },
                    "message": "I agree with @Jie, dbus objects should not be created here. Not every mux is related to PCIeSlot."
                },
                {
                    "file": "src/Overlay.cpp",
                    "line": 159,
                    "reviewer": {
                        "name": "Vijay Khemka",
                        "email": "vijaykhemkalinux@gmail.com",
                        "username": "vijaykhemka"
                    },
                    "message": "I agree that not every channel or mux would be a slot, I guess I am adding as unknown slot type even though it is not even defined. So I should have dbus interface only if slot type is defined by user in config file. If it is simply defining channel name and not defining array of SlotName and SlotType then we will consider particular channel is not a slot. Please let me know if I add a follow patch or fix this patch. As it creates lots of issues modifying a patch in a series."
                }
            ],
            "files": [
                {
                    "file": "/COMMIT_MSG",
                    "type": "ADDED",
                    "insertions": 20,
                    "deletions": 0
                },
                {
                    "file": "include/Overlay.hpp",
                    "type": "MODIFIED",
                    "insertions": 2,
                    "deletions": -1
                },
                {
                    "file": "src/EntityManager.cpp",
                    "type": "MODIFIED",
                    "insertions": 1,
                    "deletions": -1
                },
                {
                    "file": "src/Overlay.cpp",
                    "type": "MODIFIED",
                    "insertions": 38,
                    "deletions": -5
                }
            ],
            "sizeInsertions": 41,
            "sizeDeletions": 7
        },
        {
            "number": 5,
            "revision": "1b5d61da4554e9e64ce037d9eaf12d35988b9474",
            "parents": [
                "a5dcce6337b0a5283cc5c327f1f0b8bbb2e4e3aa"
            ],
            "ref": "refs/changes/21/46921/5",
            "uploader": {
                "name": "Vijay Khemka",
                "email": "vijaykhemkalinux@gmail.com",
                "username": "vijaykhemka"
            },
            "createdOn": 1633569543,
            "author": {
                "name": "Vijay Khemka",
                "email": "vijaykhemkalinux@gmail.com",
                "username": "vijaykhemka"
            },
            "kind": "NO_CODE_CHANGE",
            "files": [
                {
                    "file": "/COMMIT_MSG",
                    "type": "ADDED",
                    "insertions": 20,
                    "deletions": 0
                },
                {
                    "file": "include/Overlay.hpp",
                    "type": "MODIFIED",
                    "insertions": 2,
                    "deletions": -1
                },
                {
                    "file": "src/EntityManager.cpp",
                    "type": "MODIFIED",
                    "insertions": 1,
                    "deletions": -1
                },
                {
                    "file": "src/Overlay.cpp",
                    "type": "MODIFIED",
                    "insertions": 38,
                    "deletions": -5
                }
            ],
            "sizeInsertions": 41,
            "sizeDeletions": 7
        },
        {
            "number": 6,
            "revision": "aa87ad9e77a5f82537a826880afcd650135e726e",
            "parents": [
                "738d03b6c50f6568420e603e1f6f80134938203b"
            ],
            "ref": "refs/changes/21/46921/6",
            "uploader": {
                "name": "Vijay Khemka",
                "email": "vijaykhemkalinux@gmail.com",
                "username": "vijaykhemka"
            },
            "createdOn": 1634771347,
            "author": {
                "name": "Vijay Khemka",
                "email": "vijaykhemkalinux@gmail.com",
                "username": "vijaykhemka"
            },
            "kind": "REWORK",
            "comments": [
                {
                    "file": "src/Overlay.cpp",
                    "line": 156,
                    "reviewer": {
                        "name": "Andrei Kartashev",
                        "email": "a.kartashev@yadro.com",
                        "username": "alatarum"
                    },
                    "message": "I don't remember, why did I pass this in last review, but I definitely believe, you should do find in full list here"
                },
                {
                    "file": "src/Overlay.cpp",
                    "line": 156,
                    "reviewer": {
                        "name": "Vijay Khemka",
                        "email": "vijaykhemkalinux@gmail.com",
                        "username": "vijaykhemka"
                    },
                    "message": "Sorry, this got messed up in updating other patch and undo the work being done in previous patch. Let me have a look on all patches."
                }
            ],
            "files": [
                {
                    "file": "/COMMIT_MSG",
                    "type": "ADDED",
                    "insertions": 20,
                    "deletions": 0
                },
                {
                    "file": "include/Overlay.hpp",
                    "type": "MODIFIED",
                    "insertions": 2,
                    "deletions": -1
                },
                {
                    "file": "src/EntityManager.cpp",
                    "type": "MODIFIED",
                    "insertions": 1,
                    "deletions": -1
                },
                {
                    "file": "src/Overlay.cpp",
                    "type": "MODIFIED",
                    "insertions": 32,
                    "deletions": -5
                }
            ],
            "sizeInsertions": 35,
            "sizeDeletions": 7
        },
        {
            "number": 7,
            "revision": "8999fa6b0f5579b134e78a9df2435287fff508ad",
            "parents": [
                "63cdda0ff416858196517c09fc74995bba6e2894"
            ],
            "ref": "refs/changes/21/46921/7",
            "uploader": {
                "name": "Vijay Khemka",
                "email": "vijaykhemkalinux@gmail.com",
                "username": "vijaykhemka"
            },
            "createdOn": 1635883043,
            "author": {
                "name": "Vijay Khemka",
                "email": "vijaykhemkalinux@gmail.com",
                "username": "vijaykhemka"
            },
            "kind": "REWORK",
            "files": [
                {
                    "file": "/COMMIT_MSG",
                    "type": "ADDED",
                    "insertions": 20,
                    "deletions": 0
                },
                {
                    "file": "include/Overlay.hpp",
                    "type": "MODIFIED",
                    "insertions": 2,
                    "deletions": -1
                },
                {
                    "file": "src/EntityManager.cpp",
                    "type": "MODIFIED",
                    "insertions": 1,
                    "deletions": -1
                },
                {
                    "file": "src/Overlay.cpp",
                    "type": "MODIFIED",
                    "insertions": 38,
                    "deletions": -5
                }
            ],
            "sizeInsertions": 41,
            "sizeDeletions": 7
        },
        {
            "number": 8,
            "revision": "304a20fb9e05359d210e7bfc16afed4aab7064fe",
            "parents": [
                "63cdda0ff416858196517c09fc74995bba6e2894"
            ],
            "ref": "refs/changes/21/46921/8",
            "uploader": {
                "name": "Vijay Khemka",
                "email": "vijaykhemkalinux@gmail.com",
                "username": "vijaykhemka"
            },
            "createdOn": 1636052618,
            "author": {
                "name": "Vijay Khemka",
                "email": "vijaykhemkalinux@gmail.com",
                "username": "vijaykhemka"
            },
            "kind": "REWORK",
            "files": [
                {
                    "file": "/COMMIT_MSG",
                    "type": "ADDED",
                    "insertions": 20,
                    "deletions": 0
                },
                {
                    "file": "include/Overlay.hpp",
                    "type": "MODIFIED",
                    "insertions": 2,
                    "deletions": -1
                },
                {
                    "file": "src/EntityManager.cpp",
                    "type": "MODIFIED",
                    "insertions": 1,
                    "deletions": -1
                },
                {
                    "file": "src/Overlay.cpp",
                    "type": "MODIFIED",
                    "insertions": 45,
                    "deletions": -5
                }
            ],
            "sizeInsertions": 48,
            "sizeDeletions": 7
        },
        {
            "number": 9,
            "revision": "16f95e4a01136bbdda728b711b73e8fd87a3c78d",
            "parents": [
                "45203afab5ebd84b7955ee13df89e6e948169a75"
            ],
            "ref": "refs/changes/21/46921/9",
            "uploader": {
                "name": "Vijay Khemka",
                "email": "vijaykhemkalinux@gmail.com",
                "username": "vijaykhemka"
            },
            "createdOn": 1636757776,
            "author": {
                "name": "Vijay Khemka",
                "email": "vijaykhemkalinux@gmail.com",
                "username": "vijaykhemka"
            },
            "kind": "NO_CODE_CHANGE",
            "files": [
                {
                    "file": "/COMMIT_MSG",
                    "type": "ADDED",
                    "insertions": 20,
                    "deletions": 0
                },
                {
                    "file": "include/Overlay.hpp",
                    "type": "MODIFIED",
                    "insertions": 2,
                    "deletions": -1
                },
                {
                    "file": "src/EntityManager.cpp",
                    "type": "MODIFIED",
                    "insertions": 1,
                    "deletions": -1
                },
                {
                    "file": "src/Overlay.cpp",
                    "type": "MODIFIED",
                    "insertions": 45,
                    "deletions": -5
                }
            ],
            "sizeInsertions": 48,
            "sizeDeletions": 7
        }
    ]
}