{
    "project": "openbmc/host-error-monitor",
    "branch": "master",
    "id": "Id264aeb691e49bb1795dd544f83f8e6d37f2c9fe",
    "number": 52018,
    "subject": "Rename the err_pin_monitor to err_pin_timeout_monitor",
    "owner": {
        "name": "Jason Bills",
        "email": "jason.m.bills@linux.intel.com",
        "username": "jmbills"
    },
    "url": "https://gerrit.openbmc.org/c/openbmc/host-error-monitor/+/52018",
    "commitMessage": "Rename the err_pin_monitor to err_pin_timeout_monitor\n\nI will need to add a non-polling monitor for the ERR pin signals, so\nthis renames the current polling err_pin_monitor as an\nerr_pin_timeout_monitor.\n\nTested:\nConfirmed that the ERR pin timeout event is still logged.\n\nSigned-off-by: Jason M. Bills <jason.m.bills@intel.com>\nChange-Id: Id264aeb691e49bb1795dd544f83f8e6d37f2c9fe\n",
    "createdOn": 1647371738,
    "lastUpdated": 1647899019,
    "open": false,
    "status": "MERGED",
    "comments": [
        {
            "timestamp": 1647371738,
            "reviewer": {
                "name": "Jason Bills",
                "email": "jason.m.bills@linux.intel.com",
                "username": "jmbills"
            },
            "message": "Uploaded patch set 1."
        },
        {
            "timestamp": 1647371750,
            "reviewer": {
                "name": "OpenBMC CI",
                "email": "openbmcbump-ci@yahoo.com",
                "username": "jenkins-openbmc-ci"
            },
            "message": "Patch Set 1: Ok-To-Test+1\n\nUser approved, CI ok to start"
        },
        {
            "timestamp": 1647371750,
            "reviewer": {
                "name": "OpenBMC CI",
                "email": "openbmcbump-ci@yahoo.com",
                "username": "jenkins-openbmc-ci"
            },
            "message": "Patch Set 1: -Ok-To-Test"
        },
        {
            "timestamp": 1647371783,
            "reviewer": {
                "name": "OpenBMC CI",
                "email": "openbmcbump-ci@yahoo.com",
                "username": "jenkins-openbmc-ci"
            },
            "message": "Patch Set 1: Verified+1\n\nBuild Successful \n\nhttps://jenkins.openbmc.org/job/ci-repository/39028/ : SUCCESS"
        },
        {
            "timestamp": 1647892423,
            "reviewer": {
                "name": "Johnathan Mantey",
                "email": "johnathanx.mantey@intel.com",
                "username": "Howitzer105mm"
            },
            "message": "Patch Set 1: Code-Review+1\n\n(1 comment)"
        },
        {
            "timestamp": 1647895862,
            "reviewer": {
                "name": "Terry Duncan",
                "email": "terry.s.duncan@intel.com",
                "username": "tsdunc"
            },
            "message": "Patch Set 1: Code-Review+1"
        },
        {
            "timestamp": 1647898980,
            "reviewer": {
                "name": "Jason Bills",
                "email": "jason.m.bills@linux.intel.com",
                "username": "jmbills"
            },
            "message": "Patch Set 1: Code-Review+2"
        },
        {
            "timestamp": 1647899019,
            "reviewer": {
                "name": "Jason Bills",
                "email": "jason.m.bills@linux.intel.com",
                "username": "jmbills"
            },
            "message": "Change has been successfully merged"
        }
    ],
    "patchSets": [
        {
            "number": 1,
            "revision": "881a4e111fd017259812b3eff068abd23eac5026",
            "parents": [
                "32a90c677a07f24ca6c643a6029eec54958598e0"
            ],
            "ref": "refs/changes/18/52018/1",
            "uploader": {
                "name": "Jason Bills",
                "email": "jason.m.bills@linux.intel.com",
                "username": "jmbills"
            },
            "createdOn": 1647371738,
            "author": {
                "name": "Jason Bills",
                "email": "jason.m.bills@linux.intel.com",
                "username": "jmbills"
            },
            "kind": "REWORK",
            "comments": [
                {
                    "file": "/PATCHSET_LEVEL",
                    "line": 0,
                    "reviewer": {
                        "name": "Johnathan Mantey",
                        "email": "johnathanx.mantey@intel.com",
                        "username": "Howitzer105mm"
                    },
                    "message": "LGTM"
                }
            ],
            "files": [
                {
                    "file": "/COMMIT_MSG",
                    "type": "ADDED",
                    "insertions": 17,
                    "deletions": 0
                },
                {
                    "file": "include/error_monitors/err_pin_timeout_monitor.hpp",
                    "fileOld": "include/error_monitors/err_pin_monitor.hpp",
                    "type": "RENAMED",
                    "insertions": 6,
                    "deletions": -6
                },
                {
                    "file": "include/error_monitors/err2_monitor.hpp",
                    "type": "MODIFIED",
                    "insertions": 7,
                    "deletions": -5
                }
            ],
            "sizeInsertions": 30,
            "sizeDeletions": 11
        }
    ]
}