{
    "project": "openbmc/openbmc-test-automation",
    "branch": "master",
    "id": "Ie92f3ca0ba5a958c18c85aafa12f6464efc6e49b",
    "number": 60030,
    "subject": "Test session",
    "owner": {
        "name": "Sushil Singh",
        "email": "susilsi7@in.ibm.com",
        "username": "susilsi7"
    },
    "url": "https://gerrit.openbmc.org/c/openbmc/openbmc-test-automation/+/60030",
    "hashtags": [],
    "createdOn": 1672917595,
    "lastUpdated": 1675747049,
    "open": false,
    "status": "ABANDONED",
    "comments": [
        {
            "timestamp": 1672917595,
            "reviewer": {
                "name": "Sushil Singh",
                "email": "susilsi7@in.ibm.com",
                "username": "susilsi7"
            },
            "message": "Uploaded patch set 1."
        },
        {
            "timestamp": 1672917617,
            "reviewer": {
                "name": "OpenBMC CI",
                "email": "openbmcbump-ci@yahoo.com",
                "username": "jenkins-openbmc-ci"
            },
            "message": "Patch Set 1: Ok-To-Test+1\n\nUser approved, CI ok to start"
        },
        {
            "timestamp": 1672917617,
            "reviewer": {
                "name": "OpenBMC CI",
                "email": "openbmcbump-ci@yahoo.com",
                "username": "jenkins-openbmc-ci"
            },
            "message": "Patch Set 1: -Ok-To-Test"
        },
        {
            "timestamp": 1672917622,
            "reviewer": {
                "name": "Sushil Singh",
                "email": "susilsi7@in.ibm.com",
                "username": "susilsi7"
            },
            "message": "Uploaded patch set 2: Commit message was updated."
        },
        {
            "timestamp": 1672917636,
            "reviewer": {
                "name": "OpenBMC CI",
                "email": "openbmcbump-ci@yahoo.com",
                "username": "jenkins-openbmc-ci"
            },
            "message": "Patch Set 2: Ok-To-Test+1\n\nUser approved, CI ok to start"
        },
        {
            "timestamp": 1672917637,
            "reviewer": {
                "name": "OpenBMC CI",
                "email": "openbmcbump-ci@yahoo.com",
                "username": "jenkins-openbmc-ci"
            },
            "message": "Patch Set 2: -Ok-To-Test"
        },
        {
            "timestamp": 1672917637,
            "reviewer": {
                "name": "OpenBMC CI",
                "email": "openbmcbump-ci@yahoo.com",
                "username": "jenkins-openbmc-ci"
            },
            "message": "Patch Set 1: Verified-1\n\nBuild Failed \n\nhttps://jenkins.openbmc.org/job/ci-repository/58615/ : ABORTED"
        },
        {
            "timestamp": 1672917665,
            "reviewer": {
                "name": "OpenBMC CI",
                "email": "openbmcbump-ci@yahoo.com",
                "username": "jenkins-openbmc-ci"
            },
            "message": "Patch Set 2: Verified+1\n\nBuild Successful \n\nhttps://jenkins.openbmc.org/job/ci-repository/58616/ : SUCCESS"
        },
        {
            "timestamp": 1672917783,
            "reviewer": {
                "name": "Sushil Singh",
                "email": "susilsi7@in.ibm.com",
                "username": "susilsi7"
            },
            "message": "Removed cc Anusha Dathatri <adathatr@in.ibm.com>."
        },
        {
            "timestamp": 1673356438,
            "reviewer": {
                "name": "Sushil Singh",
                "email": "susilsi7@in.ibm.com",
                "username": "susilsi7"
            },
            "message": "Uploaded patch set 3.\n\nOutdated Votes:\n* Verified+1 (copy condition: \"changekind:NO_CHANGE OR changekind:NO_CODE_CHANGE\")\n"
        },
        {
            "timestamp": 1673356500,
            "reviewer": {
                "name": "OpenBMC CI",
                "email": "openbmcbump-ci@yahoo.com",
                "username": "jenkins-openbmc-ci"
            },
            "message": "Patch Set 3: Ok-To-Test+1\n\nUser approved, CI ok to start"
        },
        {
            "timestamp": 1673356500,
            "reviewer": {
                "name": "OpenBMC CI",
                "email": "openbmcbump-ci@yahoo.com",
                "username": "jenkins-openbmc-ci"
            },
            "message": "Patch Set 3: -Ok-To-Test"
        },
        {
            "timestamp": 1673356525,
            "reviewer": {
                "name": "OpenBMC CI",
                "email": "openbmcbump-ci@yahoo.com",
                "username": "jenkins-openbmc-ci"
            },
            "message": "Patch Set 3: Verified+1\n\nBuild Successful \n\nhttps://jenkins.openbmc.org/job/ci-repository/58860/ : SUCCESS"
        },
        {
            "timestamp": 1673357330,
            "reviewer": {
                "name": "Sushil Singh",
                "email": "susilsi7@in.ibm.com",
                "username": "susilsi7"
            },
            "message": "Uploaded patch set 4.\n\nOutdated Votes:\n* Verified+1 (copy condition: \"changekind:NO_CHANGE OR changekind:NO_CODE_CHANGE\")\n"
        },
        {
            "timestamp": 1673357359,
            "reviewer": {
                "name": "OpenBMC CI",
                "email": "openbmcbump-ci@yahoo.com",
                "username": "jenkins-openbmc-ci"
            },
            "message": "Patch Set 4: Ok-To-Test+1\n\nUser approved, CI ok to start"
        },
        {
            "timestamp": 1673357359,
            "reviewer": {
                "name": "OpenBMC CI",
                "email": "openbmcbump-ci@yahoo.com",
                "username": "jenkins-openbmc-ci"
            },
            "message": "Patch Set 4: -Ok-To-Test"
        },
        {
            "timestamp": 1673357388,
            "reviewer": {
                "name": "OpenBMC CI",
                "email": "openbmcbump-ci@yahoo.com",
                "username": "jenkins-openbmc-ci"
            },
            "message": "Patch Set 4: Verified+1\n\nBuild Successful \n\nhttps://jenkins.openbmc.org/job/ci-repository/58862/ : SUCCESS"
        },
        {
            "timestamp": 1673357856,
            "reviewer": {
                "name": "Sushil Singh",
                "email": "susilsi7@in.ibm.com",
                "username": "susilsi7"
            },
            "message": "Removed cc Anusha Dathatri <adathatr@in.ibm.com>."
        },
        {
            "timestamp": 1675747049,
            "reviewer": {
                "name": "Sushil Singh",
                "email": "susilsi7@in.ibm.com",
                "username": "susilsi7"
            },
            "message": "Abandoned\n\nThis patch is not needed."
        }
    ],
    "patchSets": [
        {
            "number": 1,
            "revision": "21e4d52f67292695517e8d933e0f68f29952c7a3",
            "parents": [
                "7e49fd5dca47b5ecd554fe011edaaad82fe61184"
            ],
            "ref": "refs/changes/30/60030/1",
            "uploader": {
                "name": "Sushil Singh",
                "email": "susilsi7@in.ibm.com",
                "username": "susilsi7"
            },
            "createdOn": 1672917595,
            "author": {
                "name": "Sushil Singh",
                "email": "susilsi7@in.ibm.com",
                "username": "susilsi7"
            },
            "kind": "REWORK",
            "files": [
                {
                    "file": "/COMMIT_MSG",
                    "type": "ADDED",
                    "insertions": 10,
                    "deletions": 0
                },
                {
                    "file": "openpower/ext_interfaces/test_lock_management.robot",
                    "type": "MODIFIED",
                    "insertions": 26,
                    "deletions": -4
                }
            ],
            "sizeInsertions": 36,
            "sizeDeletions": 4
        },
        {
            "number": 2,
            "revision": "f4c3e675be9c2b363964b2ece287b4700cdd2e1a",
            "parents": [
                "7e49fd5dca47b5ecd554fe011edaaad82fe61184"
            ],
            "ref": "refs/changes/30/60030/2",
            "uploader": {
                "name": "Sushil Singh",
                "email": "susilsi7@in.ibm.com",
                "username": "susilsi7"
            },
            "createdOn": 1672917622,
            "author": {
                "name": "Sushil Singh",
                "email": "susilsi7@in.ibm.com",
                "username": "susilsi7"
            },
            "kind": "NO_CODE_CHANGE",
            "files": [
                {
                    "file": "/COMMIT_MSG",
                    "type": "ADDED",
                    "insertions": 10,
                    "deletions": 0
                },
                {
                    "file": "openpower/ext_interfaces/test_lock_management.robot",
                    "type": "MODIFIED",
                    "insertions": 26,
                    "deletions": -4
                }
            ],
            "sizeInsertions": 36,
            "sizeDeletions": 4
        },
        {
            "number": 3,
            "revision": "6264bbdd9bf946422b4b8ccfb810954e1ea1c568",
            "parents": [
                "7e49fd5dca47b5ecd554fe011edaaad82fe61184"
            ],
            "ref": "refs/changes/30/60030/3",
            "uploader": {
                "name": "Sushil Singh",
                "email": "susilsi7@in.ibm.com",
                "username": "susilsi7"
            },
            "createdOn": 1673356438,
            "author": {
                "name": "Sushil Singh",
                "email": "susilsi7@in.ibm.com",
                "username": "susilsi7"
            },
            "kind": "REWORK",
            "files": [
                {
                    "file": "/COMMIT_MSG",
                    "type": "ADDED",
                    "insertions": 10,
                    "deletions": 0
                },
                {
                    "file": "openpower/ext_interfaces/test_lock_management.robot",
                    "type": "MODIFIED",
                    "insertions": 69,
                    "deletions": -4
                }
            ],
            "sizeInsertions": 79,
            "sizeDeletions": 4
        },
        {
            "number": 4,
            "revision": "da82973eb58d6b98eb191e72ed5b167820c16e51",
            "parents": [
                "7e49fd5dca47b5ecd554fe011edaaad82fe61184"
            ],
            "ref": "refs/changes/30/60030/4",
            "uploader": {
                "name": "Sushil Singh",
                "email": "susilsi7@in.ibm.com",
                "username": "susilsi7"
            },
            "createdOn": 1673357330,
            "author": {
                "name": "Sushil Singh",
                "email": "susilsi7@in.ibm.com",
                "username": "susilsi7"
            },
            "kind": "REWORK",
            "files": [
                {
                    "file": "/COMMIT_MSG",
                    "type": "ADDED",
                    "insertions": 10,
                    "deletions": 0
                },
                {
                    "file": "lib/resource.robot",
                    "type": "MODIFIED",
                    "insertions": 6,
                    "deletions": -6
                },
                {
                    "file": "openpower/ext_interfaces/test_lock_management.robot",
                    "type": "MODIFIED",
                    "insertions": 57,
                    "deletions": -4
                }
            ],
            "sizeInsertions": 73,
            "sizeDeletions": 10
        }
    ]
}